secrethelper/__init__.py
secrethelper/cli.py
secrethelper/core.py
secrethelper/release.py
secrethelper/secrets-example.toml
pysecrethelper-0.1.1.dist-info/LICENSE
pysecrethelper-0.1.1.dist-info/METADATA
pysecrethelper-0.1.1.dist-info/WHEEL
pysecrethelper-0.1.1.dist-info/entry_points.txt
pysecrethelper-0.1.1.dist-info/top_level.txt
pysecrethelper-0.1.1.dist-info/RECORD
