Metadata-Version: 2.1
Name: pysecrethelper
Version: 0.1.1
Summary: ...
Author-email: Carsten Knoll <firstname.lastname@posteo.de>
License: GNU General Public License v3 (GPLv3)
Project-URL: Homepage, https://codeberg.org/cknoll/secrethelper
Classifier: Development Status :: 3 - Alpha
Classifier: Intended Audience :: Developers
Classifier: Programming Language :: Python :: 3
Requires-Python: >=3.8
License-File: LICENSE
Requires-Dist: ipydex
Requires-Dist: pyperclip
Requires-Dist: colorama
Requires-Dist: tomli >=1.1.0 ; python_version < "3.11"
